smart_on_fhir_client/__init__.py
smart_on_fhir_client/client.py
smart_on_fhir_client/partner.py
smart_on_fhir_client/requester/__init__.py
smart_on_fhir_client/requester/fhir_requester.py
smart_on_fhir_client/requester/fhir_resource.py
smart_on_fhir_client/requester/mixin.py
smart_on_fhir_client/session.py
smart_on_fhir_client/strategy.py
smart_on_fhir_client/utils.py
smart_on_fhir_client-1.0.4.dist-info/METADATA
smart_on_fhir_client-1.0.4.dist-info/WHEEL
smart_on_fhir_client-1.0.4.dist-info/LICENSE
smart_on_fhir_client-1.0.4.dist-info/RECORD
