Metadata-Version: 2.1
Name: smart-on-fhir-client
Version: 1.0.4
Summary: Smart on fhir python client
Author: Marc
Author-email: marc@synapse-medicine.com
Requires-Python: >=3.10,<4.0
Classifier: Programming Language :: Python :: 3
Classifier: Programming Language :: Python :: 3.10
Classifier: Programming Language :: Python :: 3.11
Requires-Dist: PyJWT (>=2.3.0,<3.0.0)
Requires-Dist: aiocache (>=0.11.1,<0.12.0)
Requires-Dist: cryptography (>=36.0.1,<37.0.0)
Requires-Dist: fhir.resources (>=6.2.1,<7.0.0)
Requires-Dist: fhirpy (>=1.3.0,<2.0.0)
Requires-Dist: loguru (>=0.5.3,<0.6.0)
Requires-Dist: seito (>=0.1.2,<0.2.0)
Requires-Dist: tenacity (>=8.0.1,<9.0.0)
Requires-Dist: uvicorn (>=0.17.0,<0.18.0)
